agate/__init__.py
agate/columns.py
agate/config.py
agate/csv_py3.py
agate/exceptions.py
agate/fixed.py
agate/mapped_sequence.py
agate/rows.py
agate/testcase.py
agate/type_tester.py
agate/utils.py
agate/warns.py
agate/aggregations/__init__.py
agate/aggregations/all.py
agate/aggregations/any.py
agate/aggregations/base.py
agate/aggregations/count.py
agate/aggregations/deciles.py
agate/aggregations/first.py
agate/aggregations/has_nulls.py
agate/aggregations/iqr.py
agate/aggregations/mad.py
agate/aggregations/max.py
agate/aggregations/max_length.py
agate/aggregations/max_precision.py
agate/aggregations/mean.py
agate/aggregations/median.py
agate/aggregations/min.py
agate/aggregations/mode.py
agate/aggregations/percentiles.py
agate/aggregations/quartiles.py
agate/aggregations/quintiles.py
agate/aggregations/stdev.py
agate/aggregations/sum.py
agate/aggregations/summary.py
agate/aggregations/variance.py
agate/computations/__init__.py
agate/computations/base.py
agate/computations/change.py
agate/computations/formula.py
agate/computations/percent.py
agate/computations/percent_change.py
agate/computations/percentile_rank.py
agate/computations/rank.py
agate/computations/slug.py
agate/data_types/__init__.py
agate/data_types/base.py
agate/data_types/boolean.py
agate/data_types/date.py
agate/data_types/date_time.py
agate/data_types/number.py
agate/data_types/text.py
agate/data_types/time_delta.py
agate/table/__init__.py
agate/table/aggregate.py
agate/table/bar_chart.py
agate/table/bins.py
agate/table/column_chart.py
agate/table/compute.py
agate/table/denormalize.py
agate/table/distinct.py
agate/table/exclude.py
agate/table/find.py
agate/table/from_csv.py
agate/table/from_fixed.py
agate/table/from_json.py
agate/table/from_object.py
agate/table/group_by.py
agate/table/homogenize.py
agate/table/join.py
agate/table/limit.py
agate/table/line_chart.py
agate/table/merge.py
agate/table/normalize.py
agate/table/order_by.py
agate/table/pivot.py
agate/table/print_bars.py
agate-1.14.0.dist-info/licenses/AUTHORS.rst
agate-1.14.0.dist-info/licenses/COPYING
agate-1.14.0.dist-info/METADATA
agate-1.14.0.dist-info/WHEEL
agate-1.14.0.dist-info/top_level.txt
agate-1.14.0.dist-info/RECORD
